kedro_popmon/__init__.py
kedro_popmon/framework/__init__.py
kedro_popmon/framework/kedro_popmon.py
kedro_popmon/framework/cli/__init__.py
kedro_popmon/framework/cli/cli.py
kedro_popmon-0.1.0.dist-info/METADATA
kedro_popmon-0.1.0.dist-info/WHEEL
kedro_popmon-0.1.0.dist-info/entry_points.txt
kedro_popmon-0.1.0.dist-info/top_level.txt
kedro_popmon-0.1.0.dist-info/RECORD
